django_localflavor_lt
