Metadata-Version: 1.1
Name: django-localflavor-lt
Version: 1.1
Summary: Country-specific Django helpers for Lithuania.
Home-page: https://github.com/simukis/django-localflavor-lt
Author: Simonas Kazlauskas
Author-email: simonas@kazlauskas.me
License: BSD
Platform: UNKNOWN
Classifier: Development Status :: 5 - Production/Stable
Classifier: Environment :: Web Environment
Classifier: Framework :: Django
Classifier: Intended Audience :: Developers
Classifier: License :: OSI Approved :: BSD License
Classifier: Operating System :: OS Independent
Classifier: Programming Language :: Python
